afmt/__init__.py
afmt/afmt.py
afmt/meta.py
afmt/test.py
afmt-0.0.5.dist-info/LICENSE
afmt-0.0.5.dist-info/METADATA
afmt-0.0.5.dist-info/WHEEL
afmt-0.0.5.dist-info/top_level.txt
afmt-0.0.5.dist-info/RECORD
